{"version": 0.6, "generator": "Overpass API 0.7.62.10 2d4cfc48", "osm3s": {"timestamp_osm_base": "2026-03-01T06:19:06Z", "copyright": "The data included in this document is from www.openstreetmap.org. The data is made available under ODbL."}, "elements": [{"type": "node", "id": 13363565901, "lat": 51.3452255, "lon": 1.3882223, "tags": {"addr:housenumber": "25", "addr:street": "Leigh Road", "leisure": "fitness_centre", "name": "Obsidian", "opening_hours": "Mo-Fr 05:00-22:00; Sa 08:00-20:00; Su 08:00-18:00", "website": "https://m.facebook.com/61571690123400/"}}, {"type": "node", "id": 13527281995, "lat": 51.3332034, "lon": 1.4185623, "tags": {"addr:housename": "Union Yoga Studio", "addr:housenumber": "25-27", "addr:street": "Queen Street", "leisure": "fitness_centre", "sport": "yoga", "website": "https://www.unionramsgate.com/"}}]}